nice_droplets/__init__.py
nice_droplets-0.1.0.dist-info/LICENSE
nice_droplets-0.1.0.dist-info/METADATA
nice_droplets-0.1.0.dist-info/WHEEL
nice_droplets-0.1.0.dist-info/RECORD
