Metadata-Version: 2.1
Name: nice-droplets
Version: 0.1.0
Summary: A collection of helpful extensions for NiceGUI.
Home-page: https://github.com/alyxion/nice-droplets
License: MIT
Keywords: nicegui,extensions,python,ui,web
Author: Michael Ikemann
Author-email: michael.ikemann@gmail.com
Requires-Python: >=3.12
Classifier: License :: OSI Approved :: MIT License
Classifier: Programming Language :: Python :: 3
Classifier: Programming Language :: Python :: 3.12
Classifier: Programming Language :: Python :: 3.13
Requires-Dist: nicegui
Project-URL: Repository, https://github.com/alyxion/nice-droplets
